astromartini-2.1.15.dist-info/licenses/LICENSE.md
martini/__init__.py
martini/__version__.py
martini/_demo.py
martini/_demo.pyi
martini/beams.py
martini/beams.pyi
martini/datacube.py
martini/datacube.pyi
martini/martini.py
martini/martini.pyi
martini/noise.py
martini/noise.pyi
martini/spectral_models.py
martini/spectral_models.pyi
martini/sph_kernels.py
martini/sph_kernels.pyi
martini/sources/_L_align.py
martini/sources/_L_align.pyi
martini/sources/__init__.py
martini/sources/_cartesian_translation.py
martini/sources/_cartesian_translation.pyi
martini/sources/_illustris_tools.py
martini/sources/colibre_source.py
martini/sources/eagle_source.py
martini/sources/fire_source.py
martini/sources/magneticum_source.py
martini/sources/simba_source.py
martini/sources/so_source.py
martini/sources/sph_source.py
martini/sources/sph_source.pyi
martini/sources/swiftgalaxy_source.py
martini/sources/tng_source.py
astromartini-2.1.15.dist-info/METADATA
astromartini-2.1.15.dist-info/WHEEL
astromartini-2.1.15.dist-info/top_level.txt
astromartini-2.1.15.dist-info/RECORD
