Metadata-Version: 2.4
Name: astromartini
Version: 2.1.15
Summary: Synthetic datacube creation from simulations.
Author-email: Kyle Oman <kyle.a.oman@durham.ac.uk>
Project-URL: Homepage, https://github.com/kyleaoman/martini
Project-URL: Bug Tracker, https://github.com/kyleaoman/martini/issues
Project-URL: Documentation, https://martini.readthedocs.io/en/latest
Classifier: Programming Language :: Python :: 3
Classifier: License :: OSI Approved :: GNU General Public License v3 (GPLv3)
Classifier: Operating System :: OS Independent
Requires-Python: >=3.9
License-File: LICENSE.md
Requires-Dist: numpy
Requires-Dist: scipy
Requires-Dist: astropy
Requires-Dist: tqdm
Provides-Extra: hdf5-output
Requires-Dist: h5py; extra == "hdf5-output"
Provides-Extra: eaglesource
Requires-Dist: hdecompose; extra == "eaglesource"
Requires-Dist: pyread_eagle; extra == "eaglesource"
Requires-Dist: eagleSqlTools; extra == "eaglesource"
Provides-Extra: tngsource
Requires-Dist: hdecompose; extra == "tngsource"
Requires-Dist: h5py; extra == "tngsource"
Requires-Dist: requests; extra == "tngsource"
Requires-Dist: six; extra == "tngsource"
Provides-Extra: magneticumsource
Requires-Dist: g3read; extra == "magneticumsource"
Provides-Extra: simbasource
Requires-Dist: h5py; extra == "simbasource"
Provides-Extra: swiftgalaxysource
Requires-Dist: swiftsimio; extra == "swiftgalaxysource"
Requires-Dist: swiftgalaxy; extra == "swiftgalaxysource"
Provides-Extra: colibresource
Requires-Dist: swiftsimio; extra == "colibresource"
Requires-Dist: swiftgalaxy; extra == "colibresource"
Requires-Dist: velociraptor; extra == "colibresource"
Provides-Extra: firesource
Requires-Dist: utilities-awetzel; extra == "firesource"
Requires-Dist: gizmo-analysis; extra == "firesource"
Requires-Dist: halo-analysis; extra == "firesource"
Dynamic: license-file
